urd/.DS_Store
urd/__init__.py
urd/__init__tests.py
urd/apps.py
urd/iommi_admin.py
urd/iommi_admin__tests.py
urd/models.py
urd/stream_stdout.py
urd/views.py
urd/views__tests.py
urd/worker.py
urd/worker__tests.py
urd/management/.DS_Store
urd/management/__init__.py
urd/management/commands/__init__.py
urd/management/commands/monitor.py
urd/management/commands/worker.py
urd/migrations/0001_initial.py
urd/migrations/0002_alter_logitem_options_alter_task_function.py
urd/migrations/__init__.py
urd-1.3.0.dist-info/AUTHORS.rst
urd-1.3.0.dist-info/LICENSE
urd-1.3.0.dist-info/METADATA
urd-1.3.0.dist-info/WHEEL
urd-1.3.0.dist-info/top_level.txt
urd-1.3.0.dist-info/RECORD
