Metadata-Version: 2.1
Name: urd
Version: 1.3.0
Summary: Urd is a scheduler for Django projects
Home-page: https://github.com/boxed/urd
Author: Anders Hovmöller
Author-email: boxed@killingar.net
License: BSD
Keywords: urd
Classifier: Development Status :: 5 - Production/Stable
Classifier: Intended Audience :: Developers
Classifier: License :: OSI Approved :: BSD License
Classifier: Natural Language :: English
Classifier: Programming Language :: Python :: 3
License-File: LICENSE
License-File: AUTHORS.rst
Requires-Dist: Django (>=3.0)
Requires-Dist: Django (>=3.2)
Requires-Dist: setproctitle
